pyforces/__all__.py
pyforces/__init__.py
pyforces/__main__.py
pyforces/client.py
pyforces/config.py
pyforces/utils.py
pyforces/cf/execute.py
pyforces/cf/parser.py
pyforces/cf/problem.py
pyforces/cf/problem_type.py
pyforces/cmd/config.py
pyforces/cmd/gen.py
pyforces/cmd/main.py
pyforces/cmd/parse.py
pyforces/cmd/race.py
pyforces/cmd/submit.py
pyforces/cmd/test.py
pyforces_cli-0.5.0.dist-info/licenses/LICENSE
pyforces_cli-0.5.0.dist-info/METADATA
pyforces_cli-0.5.0.dist-info/WHEEL
pyforces_cli-0.5.0.dist-info/entry_points.txt
pyforces_cli-0.5.0.dist-info/top_level.txt
pyforces_cli-0.5.0.dist-info/RECORD
