Metadata-Version: 2.4
Name: pyforces-cli
Version: 0.5.0
Summary: Yet another Codeforces CLI tool
Author-email: Danqing Liu <1486701401@qq.com>
License-Expression: WTFPL
Project-URL: Homepage, https://github.com/LZDQ/pyforces
Requires-Python: >=3.10
License-File: LICENSE
Requires-Dist: cloudscraper
Requires-Dist: lxml
Requires-Dist: countdown-timer
Requires-Dist: psutil
Requires-Dist: websocket-client
Requires-Dist: markdownify
Requires-Dist: colorlog
Requires-Dist: colorama>=0.4.6
Dynamic: license-file
